[
    "{\"\\u6392\\u5e8f\": \"1\", \"\\u6d41\\u57df\": \"\\u9ad8\\u5c4f\\u6eaa\", \"\\u6c34\\u4f4d\\u7ad9\": \"\\u9054\\u897f\\u9738\\u6a02\\u6a4b\", \"\\u6c34\\u60c5\\u6642\\u9593\": \"02-03 03:10\", \"\\u76ee\\u524d\\u6c34\\u4f4d\": \"740.33\", \"\\u8b66\\u6212\\u503c\": {\"\\u4e00\\u7d1a\": \"745\", \"\\u4e8c\\u7d1a\": \"743.9\", \"\\u4e09\\u7d1a\": \"--\"}, \"\\u8b66\\u6212\": \"\\u672a\\u9054\\u8b66\\u6212\"}",
    "{\"\\u6392\\u5e8f\": \"2\", \"\\u6d41\\u57df\": \"\\u9ad8\\u5c4f\\u6eaa\", \"\\u6c34\\u4f4d\\u7ad9\": \"\\u5bf6\\u4f86\\u4e8c\\u865f\\u6a4b\", \"\\u6c34\\u60c5\\u6642\\u9593\": \"02-03 03:10\", \"\\u76ee\\u524d\\u6c34\\u4f4d\": \"398.79\", \"\\u8b66\\u6212\\u503c\": {\"\\u4e00\\u7d1a\": \"402.9\", \"\\u4e8c\\u7d1a\": \"400.8\", \"\\u4e09\\u7d1a\": \"--\"}, \"\\u8b66\\u6212\": \"\\u672a\\u9054\\u8b66\\u6212\"}",
    "{\"\\u6392\\u5e8f\": \"3\", \"\\u6d41\\u57df\": \"\\u9ad8\\u5c4f\\u6eaa\", \"\\u6c34\\u4f4d\\u7ad9\": \"\\u5c0f\\u6797\\u6a4b\", \"\\u6c34\\u60c5\\u6642\\u9593\": \"02-03 03:10\", \"\\u76ee\\u524d\\u6c34\\u4f4d\": \"338.41\", \"\\u8b66\\u6212\\u503c\": {\"\\u4e00\\u7d1a\": \"363\", \"\\u4e8c\\u7d1a\": \"361.4\", \"\\u4e09\\u7d1a\": \"--\"}, \"\\u8b66\\u6212\": \"\\u672a\\u9054\\u8b66\\u6212\"}",
    "{\"\\u6392\\u5e8f\": \"4\", \"\\u6d41\\u57df\": \"\\u9ad8\\u5c4f\\u6eaa\", \"\\u6c34\\u4f4d\\u7ad9\": \"\\u7345\\u984d\\u982d\\u6a4b\", \"\\u6c34\\u60c5\\u6642\\u9593\": \"02-03 03:10\", \"\\u76ee\\u524d\\u6c34\\u4f4d\": \"266.32\", \"\\u8b66\\u6212\\u503c\": {\"\\u4e00\\u7d1a\": \"281.7\", \"\\u4e8c\\u7d1a\": \"278.2\", \"\\u4e09\\u7d1a\": \"--\"}, \"\\u8b66\\u6212\": \"\\u672a\\u9054\\u8b66\\u6212\"}",
    "{\"\\u6392\\u5e8f\": \"5\", \"\\u6d41\\u57df\": \"\\u9ad8\\u5c4f\\u6eaa\", \"\\u6c34\\u4f4d\\u7ad9\": \"\\u56db\\u5fb7\\u5927\\u6a4b\", \"\\u6c34\\u60c5\\u6642\\u9593\": \"02-03 03:10\", \"\\u76ee\\u524d\\u6c34\\u4f4d\": \"251.43\", \"\\u8b66\\u6212\\u503c\": {\"\\u4e00\\u7d1a\": \"260.7\", \"\\u4e8c\\u7d1a\": \"259.1\", \"\\u4e09\\u7d1a\": \"--\"}, \"\\u8b66\\u6212\": \"\\u672a\\u9054\\u8b66\\u6212\"}",
    "{\"\\u6392\\u5e8f\": \"6\", \"\\u6d41\\u57df\": \"\\u9ad8\\u5c4f\\u6eaa\", \"\\u6c34\\u4f4d\\u7ad9\": \"\\u591a\\u7d0d\\u5927\\u6a4b\", \"\\u6c34\\u60c5\\u6642\\u9593\": \"02-03 03:10\", \"\\u76ee\\u524d\\u6c34\\u4f4d\": \"245.28\", \"\\u8b66\\u6212\\u503c\": {\"\\u4e00\\u7d1a\": \"250.1\", \"\\u4e8c\\u7d1a\": \"248.6\", \"\\u4e09\\u7d1a\": \"--\"}, \"\\u8b66\\u6212\": \"\\u672a\\u9054\\u8b66\\u6212\"}",
    "{\"\\u6392\\u5e8f\": \"7\", \"\\u6d41\\u57df\": \"\\u9ad8\\u5c4f\\u6eaa\", \"\\u6c34\\u4f4d\\u7ad9\": \"\\u516d\\u9f9c(1)\", \"\\u6c34\\u60c5\\u6642\\u9593\": \"02-03 03:10\", \"\\u76ee\\u524d\\u6c34\\u4f4d\": \"225.59\", \"\\u8b66\\u6212\\u503c\": {\"\\u4e00\\u7d1a\": \"238.2\", \"\\u4e8c\\u7d1a\": \"235.9\", \"\\u4e09\\u7d1a\": \"--\"}, \"\\u8b66\\u6212\": \"\\u672a\\u9054\\u8b66\\u6212\"}",
    "{\"\\u6392\\u5e8f\": \"8\", \"\\u6d41\\u57df\": \"\\u9ad8\\u5c4f\\u6eaa\", \"\\u6c34\\u4f4d\\u7ad9\": \"\\u5927\\u6d25\\u6a4b(1)\", \"\\u6c34\\u60c5\\u6642\\u9593\": \"02-03 03:10\", \"\\u76ee\\u524d\\u6c34\\u4f4d\": \"141.83\", \"\\u8b66\\u6212\\u503c\": {\"\\u4e00\\u7d1a\": \"144.9\", \"\\u4e8c\\u7d1a\": \"143.9\", \"\\u4e09\\u7d1a\": \"--\"}, \"\\u8b66\\u6212\": \"\\u672a\\u9054\\u8b66\\u6212\"}",
    "{\"\\u6392\\u5e8f\": \"9\", \"\\u6d41\\u57df\": \"\\u9ad8\\u5c4f\\u6eaa\", \"\\u6c34\\u4f4d\\u7ad9\": \"\\u65b0\\u5a01\\u5927\\u6a4b(1)\", \"\\u6c34\\u60c5\\u6642\\u9593\": \"02-03 03:10\", \"\\u76ee\\u524d\\u6c34\\u4f4d\": \"140.35\", \"\\u8b66\\u6212\\u503c\": {\"\\u4e00\\u7d1a\": \"145\", \"\\u4e8c\\u7d1a\": \"143.5\", \"\\u4e09\\u7d1a\": \"--\"}, \"\\u8b66\\u6212\": \"\\u672a\\u9054\\u8b66\\u6212\"}",
    "{\"\\u6392\\u5e8f\": \"10\", \"\\u6d41\\u57df\": \"\\u9ad8\\u5c4f\\u6eaa\", \"\\u6c34\\u4f4d\\u7ad9\": \"\\u6749\\u6797\\u5927\\u6a4b(2)\", \"\\u6c34\\u60c5\\u6642\\u9593\": \"02-03 03:10\", \"\\u76ee\\u524d\\u6c34\\u4f4d\": \"114.08\", \"\\u8b66\\u6212\\u503c\": {\"\\u4e00\\u7d1a\": \"124\", \"\\u4e8c\\u7d1a\": \"122.9\", \"\\u4e09\\u7d1a\": \"--\"}, \"\\u8b66\\u6212\": \"\\u672a\\u9054\\u8b66\\u6212\"}",
    "{\"\\u6392\\u5e8f\": \"11\", \"\\u6d41\\u57df\": \"\\u9ad8\\u5c4f\\u6eaa\", \"\\u6c34\\u4f4d\\u7ad9\": \"\\u4e09\\u5730\\u9580\", \"\\u6c34\\u60c5\\u6642\\u9593\": \"02-03 03:10\", \"\\u76ee\\u524d\\u6c34\\u4f4d\": \"106.19\", \"\\u8b66\\u6212\\u503c\": {\"\\u4e00\\u7d1a\": \"112.3\", \"\\u4e8c\\u7d1a\": \"111.1\", \"\\u4e09\\u7d1a\": \"109\"}, \"\\u8b66\\u6212\": \"\\u672a\\u9054\\u8b66\\u6212\"}",
    "{\"\\u6392\\u5e8f\": \"12\", \"\\u6d41\\u57df\": \"\\u9ad8\\u5c4f\\u6eaa\", \"\\u6c34\\u4f4d\\u7ad9\": \"\\u53e3\\u793e\\u5bcc\\u90a6\\u5927\\u6a4b\", \"\\u6c34\\u60c5\\u6642\\u9593\": \"02-03 03:10\", \"\\u76ee\\u524d\\u6c34\\u4f4d\": \"94.05\", \"\\u8b66\\u6212\\u503c\": {\"\\u4e00\\u7d1a\": \"97.7\", \"\\u4e8c\\u7d1a\": \"96.3\", \"\\u4e09\\u7d1a\": \"--\"}, \"\\u8b66\\u6212\": \"\\u672a\\u9054\\u8b66\\u6212\"}",
    "{\"\\u6392\\u5e8f\": \"13\", \"\\u6d41\\u57df\": \"\\u9ad8\\u5c4f\\u6eaa\", \"\\u6c34\\u4f4d\\u7ad9\": \"\\u6e9d\\u576a\\u6a4b\", \"\\u6c34\\u60c5\\u6642\\u9593\": \"02-03 03:10\", \"\\u76ee\\u524d\\u6c34\\u4f4d\": \"90.62\", \"\\u8b66\\u6212\\u503c\": {\"\\u4e00\\u7d1a\": \"96.1\", \"\\u4e8c\\u7d1a\": \"95.3\", \"\\u4e09\\u7d1a\": \"--\"}, \"\\u8b66\\u6212\": \"\\u672a\\u9054\\u8b66\\u6212\"}",
    "{\"\\u6392\\u5e8f\": \"14\", \"\\u6d41\\u57df\": \"\\u9ad8\\u5c4f\\u6eaa\", \"\\u6c34\\u4f4d\\u7ad9\": \"\\u897f\\u5713\\u6f6d\\u6a4b\", \"\\u6c34\\u60c5\\u6642\\u9593\": \"02-03 03:10\", \"\\u76ee\\u524d\\u6c34\\u4f4d\": \"57.85\", \"\\u8b66\\u6212\\u503c\": {\"\\u4e00\\u7d1a\": \"63.8\", \"\\u4e8c\\u7d1a\": \"62.7\", \"\\u4e09\\u7d1a\": \"--\"}, \"\\u8b66\\u6212\": \"\\u672a\\u9054\\u8b66\\u6212\"}",
    "{\"\\u6392\\u5e8f\": \"15\", \"\\u6d41\\u57df\": \"\\u9ad8\\u5c4f\\u6eaa\", \"\\u6c34\\u4f4d\\u7ad9\": \"\\u7f8e\\u6fc3\\u6a4b\", \"\\u6c34\\u60c5\\u6642\\u9593\": \"02-03 03:10\", \"\\u76ee\\u524d\\u6c34\\u4f4d\": \"41.61\", \"\\u8b66\\u6212\\u503c\": {\"\\u4e00\\u7d1a\": \"46.7\", \"\\u4e8c\\u7d1a\": \"45.6\", \"\\u4e09\\u7d1a\": \"--\"}, \"\\u8b66\\u6212\": \"\\u672a\\u9054\\u8b66\\u6212\"}",
    "{\"\\u6392\\u5e8f\": \"16\", \"\\u6d41\\u57df\": \"\\u9ad8\\u5c4f\\u6eaa\", \"\\u6c34\\u4f4d\\u7ad9\": \"\\u65d7\\u5c71\\u6a4b\", \"\\u6c34\\u60c5\\u6642\\u9593\": \"02-03 03:10\", \"\\u76ee\\u524d\\u6c34\\u4f4d\": \"35.04\", \"\\u8b66\\u6212\\u503c\": {\"\\u4e00\\u7d1a\": \"45.1\", \"\\u4e8c\\u7d1a\": \"44.1\", \"\\u4e09\\u7d1a\": \"--\"}, \"\\u8b66\\u6212\": \"\\u672a\\u9054\\u8b66\\u6212\"}",
    "{\"\\u6392\\u5e8f\": \"17\", \"\\u6d41\\u57df\": \"\\u9ad8\\u5c4f\\u6eaa\", \"\\u6c34\\u4f4d\\u7ad9\": \"\\u91cc\\u5dba\\u5927\\u6a4b\", \"\\u6c34\\u60c5\\u6642\\u9593\": \"02-03 03:10\", \"\\u76ee\\u524d\\u6c34\\u4f4d\": \"22.09\", \"\\u8b66\\u6212\\u503c\": {\"\\u4e00\\u7d1a\": \"32\", \"\\u4e8c\\u7d1a\": \"30.7\", \"\\u4e09\\u7d1a\": \"30\"}, \"\\u8b66\\u6212\": \"\\u672a\\u9054\\u8b66\\u6212\"}",
    "{\"\\u6392\\u5e8f\": \"18\", \"\\u6d41\\u57df\": \"\\u9ad8\\u5c4f\\u6eaa\", \"\\u6c34\\u4f4d\\u7ad9\": \"\\u9ad8\\u5c4f\\u5927\\u6a4b\", \"\\u6c34\\u60c5\\u6642\\u9593\": \"02-03 03:10\", \"\\u76ee\\u524d\\u6c34\\u4f4d\": \"8.99\", \"\\u8b66\\u6212\\u503c\": {\"\\u4e00\\u7d1a\": \"17.9\", \"\\u4e8c\\u7d1a\": \"16.6\", \"\\u4e09\\u7d1a\": \"13.2\"}, \"\\u8b66\\u6212\": \"\\u672a\\u9054\\u8b66\\u6212\"}",
    "{\"\\u6392\\u5e8f\": \"19\", \"\\u6d41\\u57df\": \"\\u9ad8\\u5c4f\\u6eaa\", \"\\u6c34\\u4f4d\\u7ad9\": \"\\u842c\\u5927\\u5927\\u6a4b\", \"\\u6c34\\u60c5\\u6642\\u9593\": \"02-03 03:10\", \"\\u76ee\\u524d\\u6c34\\u4f4d\": \"4.45\", \"\\u8b66\\u6212\\u503c\": {\"\\u4e00\\u7d1a\": \"13.3\", \"\\u4e8c\\u7d1a\": \"12.2\", \"\\u4e09\\u7d1a\": \"10.2\"}, \"\\u8b66\\u6212\": \"\\u672a\\u9054\\u8b66\\u6212\"}"
]